{"pageProps":{"itemData":{"url_name":"10010-mejiro-mcqueen","support_id":10010,"char_id":1013,"char_name":"Mejiro McQueen","name_jp":"メジロマックイーン","name_ko":"메지로 맥퀸","name_tw":"目白麥昆","rarity":1,"type":"stamina","obtained":"gacha","release":"2021-02-24","release_ko":"2022-06-20","release_zh_tw":"2022-06-27","release_en":"2025-06-26","effects":[[1,5,-1,-1,-1,15,-1,-1,-1,20,-1,-1],[2,-1,10,-1,15,15,-1,-1,25,-1,-1,-1],[6,-1,-1,-1,-1,-1,-1,-1,-1,1,-1,-1],[14,-1,10,-1,15,15,-1,-1,20,-1,-1,-1],[15,-1,1,-1,1,1,-1,-1,5,-1,-1,-1],[16,-1,1,-1,5,5,-1,-1,10,-1,-1,-1],[19,5,-1,-1,-1,35,-1,-1,-1,50,-1,-1]],"hints":{"hint_skills":[200172,200062,200562,200742,201352,201182,201192,201372],"hint_others":[{"hint_type":2,"hint_value":6},{"hint_type":4,"hint_value":2}]},"event_skills":[200532]},"eventData":{"ja":"{\"random\":[{\"n\":\"体重を保つ為\",\"c\":[{\"o\":\"レースが終わるまで頑張って耐える\",\"r\":[{\"t\":\"en\",\"v\":\"-10\"},{\"t\":\"st\",\"v\":\"+15\"},{\"t\":\"bo\",\"v\":\"+5\"}]},{\"o\":\"食べた分だけ走れば問題ない\",\"r\":[{\"t\":\"me\",\"v\":\"+4\"},{\"t\":\"st\",\"v\":\"+5\"},{\"t\":\"bo\",\"v\":\"+5\"}]}]},{\"n\":\"高みに至る為\",\"c\":[{\"o\":\"スタミナと根性を鍛える\",\"r\":[{\"t\":\"st\",\"v\":\"+5\"},{\"t\":\"gu\",\"v\":\"+5\"},{\"t\":\"bo\",\"v\":\"+5\"}]},{\"o\":\"スタートダッシュを意識する\",\"r\":[{\"t\":\"sk\",\"v\":\"+1\",\"d\":200532},{\"t\":\"bo\",\"v\":\"+5\"}]}]}]}","ko":"{\"random\":[{\"n\":\"몸무게를 유지하기 위해\",\"c\":[{\"o\":\"レースが終わるまで頑張って耐える\",\"r\":[{\"t\":\"en\",\"v\":\"-10\"},{\"t\":\"st\",\"v\":\"+15\"},{\"t\":\"bo\",\"v\":\"+5\"}]},{\"o\":\"食べた分だけ走れば問題ない\",\"r\":[{\"t\":\"me\",\"v\":\"+4\"},{\"t\":\"st\",\"v\":\"+5\"},{\"t\":\"bo\",\"v\":\"+5\"}]}]},{\"n\":\"정점에 다다르기 위해\",\"c\":[{\"o\":\"スタミナと根性を鍛える\",\"r\":[{\"t\":\"st\",\"v\":\"+5\"},{\"t\":\"gu\",\"v\":\"+5\"},{\"t\":\"bo\",\"v\":\"+5\"}]},{\"o\":\"スタートダッシュを意識する\",\"r\":[{\"t\":\"sk\",\"v\":\"+1\",\"d\":200532},{\"t\":\"bo\",\"v\":\"+5\"}]}]}]}","zh_tw":"{\"random\":[{\"n\":\"為了維持體重\",\"c\":[{\"o\":\"レースが終わるまで頑張って耐える\",\"r\":[{\"t\":\"en\",\"v\":\"-10\"},{\"t\":\"st\",\"v\":\"+15\"},{\"t\":\"bo\",\"v\":\"+5\"}]},{\"o\":\"食べた分だけ走れば問題ない\",\"r\":[{\"t\":\"me\",\"v\":\"+4\"},{\"t\":\"st\",\"v\":\"+5\"},{\"t\":\"bo\",\"v\":\"+5\"}]}]},{\"n\":\"為了達到巔峰\",\"c\":[{\"o\":\"スタミナと根性を鍛える\",\"r\":[{\"t\":\"st\",\"v\":\"+5\"},{\"t\":\"gu\",\"v\":\"+5\"},{\"t\":\"bo\",\"v\":\"+5\"}]},{\"o\":\"スタートダッシュを意識する\",\"r\":[{\"t\":\"sk\",\"v\":\"+1\",\"d\":200532},{\"t\":\"bo\",\"v\":\"+5\"}]}]}]}","en":"{\"random\":[{\"n\":\"To Maintain My Weight\",\"c\":[{\"o\":\"レースが終わるまで頑張って耐える\",\"r\":[{\"t\":\"en\",\"v\":\"-10\"},{\"t\":\"st\",\"v\":\"+15\"},{\"t\":\"bo\",\"v\":\"+5\"}]},{\"o\":\"食べた分だけ走れば問題ない\",\"r\":[{\"t\":\"me\",\"v\":\"+4\"},{\"t\":\"st\",\"v\":\"+5\"},{\"t\":\"bo\",\"v\":\"+5\"}]}]},{\"n\":\"To Reach the Greatest Heights\",\"c\":[{\"o\":\"スタミナと根性を鍛える\",\"r\":[{\"t\":\"st\",\"v\":\"+5\"},{\"t\":\"gu\",\"v\":\"+5\"},{\"t\":\"bo\",\"v\":\"+5\"}]},{\"o\":\"スタートダッシュを意識する\",\"r\":[{\"t\":\"sk\",\"v\":\"+1\",\"d\":200532},{\"t\":\"bo\",\"v\":\"+5\"}]}]}]}"},"profileUrlName":"mejiro-mcqueen"},"__N_SSG":true}