{"pageProps":{"itemData":{"url_name":"10086-yamanin-zephyr","support_id":10086,"char_id":1078,"char_name":"Yamanin Zephyr","name_jp":"ヤマニンゼファー","name_ko":"야마닌 제퍼","name_tw":"山人西風","rarity":1,"type":"guts","obtained":"gacha","release":"2022-12-20","release_ko":"2024-04-09","release_zh_tw":"2024-04-23","effects":[[1,5,-1,-1,10,10,-1,-1,15,-1,-1,-1],[3,-1,-1,-1,-1,-1,-1,-1,-1,1,-1,-1],[6,-1,1,-1,1,1,-1,-1,1,-1,-1,-1],[8,1,-1,-1,-1,5,-1,-1,-1,10,-1,-1],[14,10,-1,-1,-1,20,-1,-1,-1,25,-1,-1],[15,-1,1,-1,1,1,-1,-1,5,-1,-1,-1],[16,-1,1,-1,5,5,-1,-1,10,-1,-1,-1],[17,-1,1,-1,1,1,-1,-1,2,-1,-1,-1],[18,-1,5,-1,20,20,-1,-1,30,-1,-1,-1],[19,-1,5,-1,20,20,-1,-1,35,-1,-1,-1]],"hints":{"hint_skills":[200192,200302,201532,201042,201052,201072,201112,202412,200342],"hint_others":[{"hint_type":1,"hint_value":1},{"hint_type":3,"hint_value":1},{"hint_type":4,"hint_value":6}]},"event_skills":[202412]},"eventData":{"ja":"{\"random\":[{\"n\":\"風は、自由\",\"c\":[{\"o\":\"早速、頑張れそう！\",\"r\":[{\"t\":\"sp\",\"v\":\"+10\"},{\"t\":\"gu\",\"v\":\"+5\"},{\"t\":\"bo\",\"v\":\"+5\",\"d\":1078}]},{\"o\":\"もっと風に乗りたくなるな\",\"r\":[{\"t\":\"me\",\"v\":\"+4\"},{\"t\":\"bo\",\"v\":\"+5\",\"d\":1078}]}]},{\"n\":\"風は、果てなく\",\"c\":[{\"o\":\"全能感はありそう\",\"r\":[{\"t\":\"sp\",\"v\":\"+3\"},{\"t\":\"po\",\"v\":\"+3\"},{\"t\":\"gu\",\"v\":\"+3\"},{\"t\":\"bo\",\"v\":\"+5\",\"d\":1078}]},{\"o\":\"心地よさそうではあるな\",\"r\":[{\"t\":\"sk\",\"v\":\"+1\",\"d\":202412},{\"t\":\"bo\",\"v\":\"+5\",\"d\":1078}]}]}]}","ko":"{\"random\":[{\"n\":\"바람은, 자유\",\"c\":[{\"o\":\"早速、頑張れそう！\",\"r\":[{\"t\":\"sp\",\"v\":\"+10\"},{\"t\":\"gu\",\"v\":\"+5\"},{\"t\":\"bo\",\"v\":\"+5\",\"d\":1078}]},{\"o\":\"もっと風に乗りたくなるな\",\"r\":[{\"t\":\"me\",\"v\":\"+4\"},{\"t\":\"bo\",\"v\":\"+5\",\"d\":1078}]}]},{\"n\":\"바람은, 끝없이\",\"c\":[{\"o\":\"全能感はありそう\",\"r\":[{\"t\":\"sp\",\"v\":\"+3\"},{\"t\":\"po\",\"v\":\"+3\"},{\"t\":\"gu\",\"v\":\"+3\"},{\"t\":\"bo\",\"v\":\"+5\",\"d\":1078}]},{\"o\":\"心地よさそうではあるな\",\"r\":[{\"t\":\"sk\",\"v\":\"+1\",\"d\":202412},{\"t\":\"bo\",\"v\":\"+5\",\"d\":1078}]}]}]}","zh_tw":"{\"random\":[{\"n\":\"自由的風\",\"c\":[{\"o\":\"早速、頑張れそう！\",\"r\":[{\"t\":\"sp\",\"v\":\"+10\"},{\"t\":\"gu\",\"v\":\"+5\"},{\"t\":\"bo\",\"v\":\"+5\",\"d\":1078}]},{\"o\":\"もっと風に乗りたくなるな\",\"r\":[{\"t\":\"me\",\"v\":\"+4\"},{\"t\":\"bo\",\"v\":\"+5\",\"d\":1078}]}]},{\"n\":\"無盡的風\",\"c\":[{\"o\":\"全能感はありそう\",\"r\":[{\"t\":\"sp\",\"v\":\"+3\"},{\"t\":\"po\",\"v\":\"+3\"},{\"t\":\"gu\",\"v\":\"+3\"},{\"t\":\"bo\",\"v\":\"+5\",\"d\":1078}]},{\"o\":\"心地よさそうではあるな\",\"r\":[{\"t\":\"sk\",\"v\":\"+1\",\"d\":202412},{\"t\":\"bo\",\"v\":\"+5\",\"d\":1078}]}]}]}","en":"{\"random\":[{\"n\":\"風は、自由\",\"c\":[{\"o\":\"早速、頑張れそう！\",\"r\":[{\"t\":\"sp\",\"v\":\"+10\"},{\"t\":\"gu\",\"v\":\"+5\"},{\"t\":\"bo\",\"v\":\"+5\",\"d\":1078}]},{\"o\":\"もっと風に乗りたくなるな\",\"r\":[{\"t\":\"me\",\"v\":\"+4\"},{\"t\":\"bo\",\"v\":\"+5\",\"d\":1078}]}]},{\"n\":\"風は、果てなく\",\"c\":[{\"o\":\"全能感はありそう\",\"r\":[{\"t\":\"sp\",\"v\":\"+3\"},{\"t\":\"po\",\"v\":\"+3\"},{\"t\":\"gu\",\"v\":\"+3\"},{\"t\":\"bo\",\"v\":\"+5\",\"d\":1078}]},{\"o\":\"心地よさそうではあるな\",\"r\":[{\"t\":\"sk\",\"v\":\"+1\",\"d\":202412},{\"t\":\"bo\",\"v\":\"+5\",\"d\":1078}]}]}]}"},"profileUrlName":"yamanin-zephyr"},"__N_SSG":true}