{"pageProps":{"itemData":{"url_name":"30143-ikuno-dictus","support_id":30143,"char_id":1063,"char_name":"Ikuno Dictus","name_jp":"イクノディクタス","name_ko":"이쿠노 딕터스","name_tw":"生野狄杜斯","rarity":3,"type":"power","obtained":"story_event","release":"2023-04-28","release_ko":"2024-08-16","release_zh_tw":"2024-08-29","effects":[[1,10,-1,-1,-1,-1,15,15,-1,-1,20,-1],[2,10,-1,-1,-1,-1,-1,40,-1,-1,-1,50],[5,-1,-1,-1,-1,-1,-1,-1,1,-1,-1,-1],[14,-1,-1,-1,-1,-1,-1,-1,-1,-1,15,30],[17,-1,-1,-1,1,-1,1,1,-1,-1,2,-1],[18,-1,-1,-1,5,-1,20,20,-1,-1,30,-1],[19,-1,-1,5,-1,-1,35,35,-1,-1,50,-1]],"hints":{"hint_skills":[201542,200482,200592,201382,201442],"hint_others":[{"hint_type":2,"hint_value":2},{"hint_type":3,"hint_value":6}]},"event_skills":[201432,201401,200781],"unique":{"level":40,"effects":[{"type":101,"value":80,"value_1":4,"value_2":2}]}},"eventData":{"ja":"{\"random\":[{\"n\":\"イクノ式万全メソッド\",\"c\":[{\"o\":\"全部1人でやるの？\",\"r\":[{\"t\":\"in\",\"v\":\"+10\"},{\"t\":\"bo\",\"v\":\"+5\",\"d\":1063}]},{\"o\":\"随分と熱心なんだね\",\"r\":[{\"t\":\"pt\",\"v\":\"+30\"},{\"t\":\"bo\",\"v\":\"+5\",\"d\":1063}]}]},{\"n\":\"イクノ式マネジメント論\",\"c\":[{\"o\":\"俺のスケジュールも見て欲しい\",\"r\":[{\"t\":\"st\",\"v\":\"+20\"},{\"t\":\"bo\",\"v\":\"+5\",\"d\":1063}]},{\"o\":\"コツとか教えて\",\"r\":[{\"t\":\"sk\",\"v\":\"+1\",\"d\":200781},{\"t\":\"bo\",\"v\":\"+5\",\"d\":1063}]}]}],\"arrows\":[{\"n\":\"ひとつひとつに、真心を\",\"c\":[{\"o\":\"\",\"r\":[{\"t\":\"po\",\"v\":\"+5\"},{\"t\":\"sk\",\"v\":\"+1\",\"d\":201432},{\"t\":\"bo\",\"v\":\"+5\",\"d\":1063}]}]},{\"n\":\"誠心誠意、感謝をこめて\",\"c\":[{\"o\":\"自分のケアも忘れずにな\",\"r\":[{\"t\":\"en\",\"v\":\"+10\"},{\"t\":\"st\",\"v\":\"+7\"},{\"t\":\"bo\",\"v\":\"+5\",\"d\":1063}]},{\"o\":\"大切に使わせてもらうよ\",\"r\":[{\"t\":\"mo\",\"v\":\"+1\"},{\"t\":\"in\",\"v\":\"+7\"},{\"t\":\"bo\",\"v\":\"+5\",\"d\":1063}]}]},{\"n\":\"心づかいは、巡り巡って\",\"c\":[{\"o\":\"\",\"r\":[{\"t\":\"po\",\"v\":\"+7\"},{\"t\":\"in\",\"v\":\"+7\"},{\"t\":\"sk\",\"v\":\"+1\",\"d\":201401},{\"t\":\"bo\",\"v\":\"+5\",\"d\":1063}]}]}]}","ko":"{\"random\":[{\"n\":\"이쿠노식 만전 메서드\",\"c\":[{\"o\":\"全部1人でやるの？\",\"r\":[{\"t\":\"in\",\"v\":\"+10\"},{\"t\":\"bo\",\"v\":\"+5\",\"d\":1063}]},{\"o\":\"随分と熱心なんだね\",\"r\":[{\"t\":\"pt\",\"v\":\"+30\"},{\"t\":\"bo\",\"v\":\"+5\",\"d\":1063}]}]},{\"n\":\"이쿠노식 매니지먼트론\",\"c\":[{\"o\":\"俺のスケジュールも見て欲しい\",\"r\":[{\"t\":\"st\",\"v\":\"+20\"},{\"t\":\"bo\",\"v\":\"+5\",\"d\":1063}]},{\"o\":\"コツとか教えて\",\"r\":[{\"t\":\"sk\",\"v\":\"+1\",\"d\":200781},{\"t\":\"bo\",\"v\":\"+5\",\"d\":1063}]}]}],\"arrows\":[{\"n\":\"하나하나에 진심으로\",\"c\":[{\"o\":\"\",\"r\":[{\"t\":\"po\",\"v\":\"+5\"},{\"t\":\"sk\",\"v\":\"+1\",\"d\":201432},{\"t\":\"bo\",\"v\":\"+5\",\"d\":1063}]}]},{\"n\":\"성심성의, 감사를 담아서\",\"c\":[{\"o\":\"自分のケアも忘れずにな\",\"r\":[{\"t\":\"en\",\"v\":\"+10\"},{\"t\":\"st\",\"v\":\"+7\"},{\"t\":\"bo\",\"v\":\"+5\",\"d\":1063}]},{\"o\":\"大切に使わせてもらうよ\",\"r\":[{\"t\":\"mo\",\"v\":\"+1\"},{\"t\":\"in\",\"v\":\"+7\"},{\"t\":\"bo\",\"v\":\"+5\",\"d\":1063}]}]},{\"n\":\"배려심은 돌고 돌아\",\"c\":[{\"o\":\"\",\"r\":[{\"t\":\"po\",\"v\":\"+7\"},{\"t\":\"in\",\"v\":\"+7\"},{\"t\":\"sk\",\"v\":\"+1\",\"d\":201401},{\"t\":\"bo\",\"v\":\"+5\",\"d\":1063}]}]}]}","zh_tw":"{\"random\":[{\"n\":\"生野式萬全的做法\",\"c\":[{\"o\":\"全部1人でやるの？\",\"r\":[{\"t\":\"in\",\"v\":\"+10\"},{\"t\":\"bo\",\"v\":\"+5\",\"d\":1063}]},{\"o\":\"随分と熱心なんだね\",\"r\":[{\"t\":\"pt\",\"v\":\"+30\"},{\"t\":\"bo\",\"v\":\"+5\",\"d\":1063}]}]},{\"n\":\"生野式管理論\",\"c\":[{\"o\":\"俺のスケジュールも見て欲しい\",\"r\":[{\"t\":\"st\",\"v\":\"+20\"},{\"t\":\"bo\",\"v\":\"+5\",\"d\":1063}]},{\"o\":\"コツとか教えて\",\"r\":[{\"t\":\"sk\",\"v\":\"+1\",\"d\":200781},{\"t\":\"bo\",\"v\":\"+5\",\"d\":1063}]}]}],\"arrows\":[{\"n\":\"對每個用品都付出真心\",\"c\":[{\"o\":\"\",\"r\":[{\"t\":\"po\",\"v\":\"+5\"},{\"t\":\"sk\",\"v\":\"+1\",\"d\":201432},{\"t\":\"bo\",\"v\":\"+5\",\"d\":1063}]}]},{\"n\":\"誠心誠意，飽含感謝\",\"c\":[{\"o\":\"自分のケアも忘れずにな\",\"r\":[{\"t\":\"en\",\"v\":\"+10\"},{\"t\":\"st\",\"v\":\"+7\"},{\"t\":\"bo\",\"v\":\"+5\",\"d\":1063}]},{\"o\":\"大切に使わせてもらうよ\",\"r\":[{\"t\":\"mo\",\"v\":\"+1\"},{\"t\":\"in\",\"v\":\"+7\"},{\"t\":\"bo\",\"v\":\"+5\",\"d\":1063}]}]},{\"n\":\"體貼之心，禮尚往來\",\"c\":[{\"o\":\"\",\"r\":[{\"t\":\"po\",\"v\":\"+7\"},{\"t\":\"in\",\"v\":\"+7\"},{\"t\":\"sk\",\"v\":\"+1\",\"d\":201401},{\"t\":\"bo\",\"v\":\"+5\",\"d\":1063}]}]}]}","en":"{\"random\":[{\"n\":\"イクノ式万全メソッド\",\"c\":[{\"o\":\"全部1人でやるの？\",\"r\":[{\"t\":\"in\",\"v\":\"+10\"},{\"t\":\"bo\",\"v\":\"+5\",\"d\":1063}]},{\"o\":\"随分と熱心なんだね\",\"r\":[{\"t\":\"pt\",\"v\":\"+30\"},{\"t\":\"bo\",\"v\":\"+5\",\"d\":1063}]}]},{\"n\":\"イクノ式マネジメント論\",\"c\":[{\"o\":\"俺のスケジュールも見て欲しい\",\"r\":[{\"t\":\"st\",\"v\":\"+20\"},{\"t\":\"bo\",\"v\":\"+5\",\"d\":1063}]},{\"o\":\"コツとか教えて\",\"r\":[{\"t\":\"sk\",\"v\":\"+1\",\"d\":200781},{\"t\":\"bo\",\"v\":\"+5\",\"d\":1063}]}]}],\"arrows\":[{\"n\":\"ひとつひとつに、真心を\",\"c\":[{\"o\":\"\",\"r\":[{\"t\":\"po\",\"v\":\"+5\"},{\"t\":\"sk\",\"v\":\"+1\",\"d\":201432},{\"t\":\"bo\",\"v\":\"+5\",\"d\":1063}]}]},{\"n\":\"誠心誠意、感謝をこめて\",\"c\":[{\"o\":\"自分のケアも忘れずにな\",\"r\":[{\"t\":\"en\",\"v\":\"+10\"},{\"t\":\"st\",\"v\":\"+7\"},{\"t\":\"bo\",\"v\":\"+5\",\"d\":1063}]},{\"o\":\"大切に使わせてもらうよ\",\"r\":[{\"t\":\"mo\",\"v\":\"+1\"},{\"t\":\"in\",\"v\":\"+7\"},{\"t\":\"bo\",\"v\":\"+5\",\"d\":1063}]}]},{\"n\":\"心づかいは、巡り巡って\",\"c\":[{\"o\":\"\",\"r\":[{\"t\":\"po\",\"v\":\"+7\"},{\"t\":\"in\",\"v\":\"+7\"},{\"t\":\"sk\",\"v\":\"+1\",\"d\":201401},{\"t\":\"bo\",\"v\":\"+5\",\"d\":1063}]}]}]}"},"profileUrlName":"ikuno-dictus"},"__N_SSG":true}